pymongoshell/__init__.py
pymongoshell/calltest.py
pymongoshell/classproxy.py
pymongoshell/demo_exists.py
pymongoshell/drop_collection.py
pymongoshell/drop_database.py
pymongoshell/errorhandling.py
pymongoshell/manydocs.py
pymongoshell/mongoclient.py
pymongoshell/mping.py
pymongoshell/pager.py
pymongoshell/smping.py
pymongoshell/so.py
pymongoshell/version.py
pymongoshell-1.2.1b5.dist-info/LICENSE
pymongoshell-1.2.1b5.dist-info/METADATA
pymongoshell-1.2.1b5.dist-info/WHEEL
pymongoshell-1.2.1b5.dist-info/top_level.txt
pymongoshell-1.2.1b5.dist-info/RECORD
